rym/alias/__about__.py
rym/alias/__init__.py
rym/alias/_alias.py
rym/alias/_aliasfrozen.py
rym/alias/_aliasresolver.py
rym/alias/_coerce.py
rym/alias/_coerce_errors.py
rym/alias/_coerce_explicit.py
rym/alias/_coerce_implicit.py
rym/alias/safesort.py
rym/alias/variation.py
rym_alias-0.2.0.dist-info/METADATA
rym_alias-0.2.0.dist-info/WHEEL
rym_alias-0.2.0.dist-info/RECORD
